prolif/__init__.py
prolif/_version.py
prolif/datafiles.py
prolif/exceptions.py
prolif/fingerprint.py
prolif/ifp.py
prolif/molecule.py
prolif/parallel.py
prolif/pickling.py
prolif/py.typed
prolif/rdkitmol.py
prolif/residue.py
prolif/typeshed.py
prolif/utils.py
prolif/data/acceptor.mol2
prolif/data/acceptor_false.mol2
prolif/data/anion.mol2
prolif/data/benzene.mol2
prolif/data/bromine.mol2
prolif/data/cation.mol2
prolif/data/cation_false.mol2
prolif/data/chlorine.mol2
prolif/data/donor.mol2
prolif/data/edgetoface.mol2
prolif/data/facetoface.mol2
prolif/data/ligand.mol2
prolif/data/metal.mol2
prolif/data/metal_false.mol2
prolif/data/mol_comment.mol2
prolif/data/top.pdb
prolif/data/traj.xtc
prolif/data/water_m2.pdb
prolif/data/water_m2.xtc
prolif/data/xbond_acceptor.mol2
prolif/data/xbond_acceptor_false_axd.mol2
prolif/data/xbond_acceptor_false_xar.mol2
prolif/data/xbond_donor.mol2
prolif/data/vina/lig.pdb
prolif/data/vina/rec.pdb
prolif/data/vina/vina_output.mol2
prolif/data/vina/vina_output.sdf
prolif/data/vina/vina_output_ligand_1.pdbqt
prolif/data/vina/vina_output_ligand_2.pdbqt
prolif/data/vina/vina_output_ligand_3.pdbqt
prolif/data/vina/vina_output_ligand_4.pdbqt
prolif/data/vina/vina_output_ligand_5.pdbqt
prolif/data/vina/vina_output_ligand_6.pdbqt
prolif/data/vina/vina_output_ligand_7.pdbqt
prolif/data/vina/vina_output_ligand_8.pdbqt
prolif/data/vina/vina_output_ligand_9.pdbqt
prolif/interactions/__init__.py
prolif/interactions/base.py
prolif/interactions/constants.py
prolif/interactions/interactions.py
prolif/interactions/utils.py
prolif/interactions/water_bridge.py
prolif/plotting/__init__.py
prolif/plotting/barcode.py
prolif/plotting/complex3d.py
prolif/plotting/residues.py
prolif/plotting/utils.py
prolif/plotting/network/__init__.py
prolif/plotting/network/lignetwork.py
prolif/plotting/network/network.css
prolif/plotting/network/network.html
prolif/plotting/network/network.js
prolif_lite-2.1.3.dist-info/licenses/LICENSE
prolif_lite-2.1.3.dist-info/METADATA
prolif_lite-2.1.3.dist-info/WHEEL
prolif_lite-2.1.3.dist-info/top_level.txt
prolif_lite-2.1.3.dist-info/RECORD
