Metadata-Version: 2.4
Name: prolif-lite
Version: 2.1.3
Summary: Interaction Fingerprints for protein-ligand docking analysis (MDAnalysis-free version)
Author-email: Cédric Bouysset <cedric@bouysset.net>
License:                                  Apache License
Project-URL: Homepage, https://github.com/rkakamilan/ProLIF
Project-URL: Documentation, https://prolif.readthedocs.io/en/stable/
Project-URL: Discussions, https://github.com/rkakamilan/ProLIF/discussions
Project-URL: Issues, https://github.com/rkakamilan/ProLIF/issues
Project-URL: Changelog, https://github.com/rkakamilan/ProLIF/blob/master/CHANGELOG.md
Keywords: science,chemistry,drug-design,cheminformatics,chemoinformatics,molecular-dynamics,interaction-fingerprint
Classifier: Development Status :: 5 - Production/Stable
Classifier: Operating System :: OS Independent
Classifier: Intended Audience :: Science/Research
Classifier: License :: OSI Approved :: Apache Software License
Classifier: Programming Language :: Python :: 3
Classifier: Programming Language :: Python :: 3.10
Classifier: Programming Language :: Python :: 3.11
Classifier: Programming Language :: Python :: 3.12
Classifier: Programming Language :: Python :: 3.13
Classifier: Topic :: Scientific/Engineering :: Bio-Informatics
Classifier: Topic :: Scientific/Engineering :: Chemistry
Requires-Python: >=3.10
License-File: LICENSE
Requires-Dist: pandas>=1.1.0
Requires-Dist: numpy<2,>=1.13.3
Requires-Dist: scipy>=1.3.0
Requires-Dist: networkx>=2.5.0
Requires-Dist: tqdm
Requires-Dist: multiprocess
Requires-Dist: dill
Provides-Extra: plots
Requires-Dist: py3Dmol; extra == "plots"
Requires-Dist: matplotlib>=3.5; extra == "plots"
Provides-Extra: tutorials
Requires-Dist: rdkit; extra == "tutorials"
Requires-Dist: matplotlib>=3.7; extra == "tutorials"
Requires-Dist: seaborn<1.0; extra == "tutorials"
Requires-Dist: pyvis; extra == "tutorials"
Requires-Dist: prolif-lite[plots]; extra == "tutorials"
Dynamic: license-file
